[
  {
    "activity_name": "Spring Fest",
    "location": "Christian Life Austin, 4700 West Gate Blvd, Austin, TX 78745",
    "date": "2025-04-12",
    "time": "10:00 AM - 1:00 PM",
    "description": "Join Christian Life Austin for a family-friendly event featuring a glow-in-the-dark Easter Egg Hunt, face painting, carnival rides, and more.",
    "additional_details": "Includes activities such as meeting the Easter Bunny, inflatables, pony rides, and a petting zoo. RSVP is encouraged.",
    "source_file": "0cc2f560c00fc00d3032cb2c47a85255.JPG"
  },
  {
    "activity_name": "Flashlight Egg Hunt",
    "location": "Old Settlers Park, 3300 E. Palm Valley Blvd., Round Rock, TX",
    "date": "2025-04-17",
    "time": "6:00 PM - 10:00 PM",
    "description": "Nighttime hunt with flashlight, followed by a movie. Pre-registration required.",
    "additional_details": "Cost: $7-$10/hunter",
    "source_file": "c86604342baa68f3edb1858fd904e4f6.JPG"
  },
  {
    "activity_name": "Eggstravaganza",
    "location": "The Fellowship Church, 3379 Gattis School Rd, Round Rock, TX",
    "date": "2025-04-12",
    "time": "10:00 AM",
    "description": "FREE EVENT with epic egg hunt with prizes, yard games, crafts, bouncy houses, and Easter fun for all!",
    "additional_details": null,
    "source_file": "c86604342baa68f3edb1858fd904e4f6.JPG"
  },
  {
    "activity_name": "Easter Fest",
    "location": "St. Philip's UMC, 16321 Great Oaks Dr, Round Rock, TX 78681, United States",
    "date": "2025-04-13",
    "time": "12:30 PM - 2:30 PM",
    "description": "A community event featuring an egg hunt, bounce house, and food.",
    "additional_details": "Free event. Invite family, friends, and neighbors.",
    "source_file": "971adb7051aaf86a9101822c491d8d91.JPG"
  },
  {
    "activity_name": "Easter EGGstravaganza!",
    "location": "King of Kings Lutheran Church, 17000 Smyers Ln, Round Rock, TX 78681, United States",
    "date": "2025-04-13",
    "time": "11:30 AM - 1:30 PM",
    "description": "Free family Easter event for all ages with Easter egg hunts, games, crafts, prizes, photos with the Easter Bunny, live music, and more.",
    "additional_details": "Concessions available for purchase. Worship at 9:00 AM, Sunday school 10:30-11:30 AM. Email kbrown@kingofkingstx.org for questions.",
    "source_file": "318184d21041fa09a01a8c08929414d1.JPG"
  },
  {
    "activity_name": "Palm Sunday Egg Hunt",
    "location": "Hillcrest Church, 3838 Steck Avenue, Austin, TX 78717",
    "date": "2025-04-13",
    "time": "1:00 PM - 2:30 PM",
    "description": "Egg hunt for preschoolers and K-5th graders with bounce houses, popcorn, and live music.",
    "additional_details": "Sunday School program starts at 11:15 AM with scavenger hunt and treats. More info at www.hillcrest.church.",
    "source_file": "3ffc036f742a50987a30369880706729.JPG"
  },
  {
    "activity_name": "2025 EGgstravaganza",
    "location": "North Austin YMCA, 11006 W Rundberg Ln, Austin, TX",
    "date": "2025-04-12",
    "time": "12 PM - 3 PM",
    "description": null,
    "additional_details": "Cost: Free"
  },
  {
    "activity_name": "Brushy Creek Egg Hunt",
    "location": "Cat Hallow Park, 8600 O'Connor Dr, Round Rock, TX",
    "date": "2025-04-12",
    "time": "10 AM - 12 PM",
    "description": null,
    "additional_details": "Cost: Free"
  },
  {
    "activity_name": "Egg Hunt & Easter Mini's",
    "location": "Pikopye's Town, 1607 Ranch Rd 620 N #100, Lakeway, TX",
    "date": "2025-04-13",
    "time": "4 PM",
    "description": null,
    "additional_details": "Cost: $45"
  },
  {
    "activity_name": "Egg Hunt",
    "location": "Adam Orgain Park, Brushy Creek Amphitheater, 1001 County Road 137, Hutto, TX 78634-2204, United States",
    "date": "2025-04-20",
    "time": "2:00 PM - 3:00 PM",
    "description": "Free kids' egg hunt for children 12 and under with 50,000 eggs to collect.",
    "additional_details": "Bring baskets and wear comfy shoes. Public event organized by Hutto Parks and Recreation and City of Hutto, TX.",
    "source_file": "16c106aa0454f33733403abca2e808cd.JPG"
  },
  {
    "activity_name": "April Family Day: Heart of the Garden",
    "location": "Umlauf Sculpture Garden & Museum, 605 Azie Morton RD Austin, TX 78704",
    "date": "2025-04-13",
    "time": "11:00 AM - 4:00 PM",
    "description": "A serene and joyful atmosphere with activities such as caricatures, community partners, crafts, storytime, sculpture searches, and garden tours.",
    "additional_details": "Free entry. RSVP at umlaufsculpture.org",
    "source_file": "09c07f3a94e7862faae9ea35c96be276.JPG"
  },
  {
    "activity_name": "Free Egg Hunt at Reach Church",
    "location": "Reach Church, 636 W Front St, Hutto, TX 78634, United States",
    "date": "2025-04-13",
    "time": "12:30 PM - 2:00 PM",
    "description": "Free Easter Egg Hunt for kids ages 1-11, divided into age groups 5 & under and 6-11 years old.",
    "additional_details": "Following the 11:30 AM service. Kona Ice and fresh burritos available. It's a fun event for the whole family.",
    "source_file": "e291d5c00782773d66cdc206d608b115.JPG"
  },
  {
    "activity_name": "Easter Jam!",
    "location": "Life Church, 1393 E Woodview Dr, Leander, TX, United States, Texas 78641",
    "date": "2025-04-13",
    "time": "3:00 PM - 4:00 PM",
    "description": "Fun, free event geared toward kids birth through 5th grade. Includes Easter discussions, activities, and an egg hunt.",
    "additional_details": "All are welcome. Invite a friend.",
    "source_file": "8c86ecc0037b7b55289396ec390abbab.JPG"
  },
  {
    "activity_name": "Healthy Kids Day and Business Fair",
    "location": "Boles Family Sports Complex West, 1500 North Mays Street, Round Rock, TX 78664, United States",
    "date": "2025-04-12",
    "time": "11:00 AM - 2:30 PM",
    "description": "Annual CHASCO Family YMCA Healthy Kids Day and Esteam Academy Children's Business Fair with activities like face painting, bouncy houses, soccer shootouts, and over 100 Children's Business Booths.",
    "additional_details": "Free family event. Students from Esteam Academy will have booths to sell their products. Live music from Round Rock School of Rock from 11am-2pm. Parking available at Boles Sports Complex West.",
    "source_file": "f05575de057034995647860ebafd5603.JPG"
  },
  {
    "activity_name": "OP Vets Easter Celebration",
    "location": "The American Legion, George Johns Post 447, 1000 N Georgetown St, Round Rock, TX 78664-4462, United States",
    "date": "2025-04-13",
    "time": "12:00 PM",
    "description": "Crawfish! Easter Egg Hunt for the kids at 2:00 PM! Bouncy house! Live music!",
    "additional_details": "Public event. Anyone on or off Facebook can attend.",
    "source_file": "2ee09fcd84fcf13b69509d26e04a25ca.JPG"
  },
  {
    "activity_name": "EGGSTRAVAGANZA - FREE Event",
    "location": "The Fellowship Church, 3379 Gattis School Rd, Round Rock, TX 78664",
    "date": "2025-04-12",
    "time": "10:00 AM",
    "description": "Epic egg hunt for kids up to 12 years old with 50 amazing prizes, including Kalahari park passes, yard game area, crafts, and bouncy houses.",
    "additional_details": "Event is public and free. Learn more at https://www.FellowshipEaster.org.",
    "source_file": "9b8895ff6609f2782a7fe5fe015ab06d.JPG"
  },
  {
    "activity_name": "Spring Community Festival",
    "location": "600 W New Hope Dr, Cedar Park, TX, United States, Texas 78613",
    "date": "2025-04-13",
    "time": "10:00 AM - 1:00 PM",
    "description": "Join us for a day of fun, faith, and fellowship! Enjoy food, inflatables, games, crafts, and more!",
    "additional_details": "Free garage sale and grand opening of the new community garden. For more information, visit: www.hpf.org/community",
    "source_file": "941c1a013f0d4960da07b083cea1d0fe.JPG"
  },
  {
    "activity_name": "Hometown's 3rd Annual Easter Eggstravaganza",
    "location": "400 E Main St, Round Rock, TX 78664, United States",
    "date": "2025-04-13",
    "time": "10:00 AM - 10:45 AM",
    "description": "Celebrate with us at our 3rd Annual Hometown Eggstravaganza. Egg hunts at 10:00 AM for ages 3 and under, and 10:45 AM for ages 4 and up.",
    "additional_details": "Bring your baskets! Event marks the 3rd anniversary of our business.",
    "source_file": "c6bf2b49bb67cadb6f0cb473386f5d9e.JPG"
  },
  {
    "activity_name": "Spring Fling and Artisan's Market",
    "location": "Rockbridge Church, 2001 West New Hope Drive, Cedar Park, TX, United States, Texas 78613",
    "date": "2025-04-13",
    "time": "10:00 AM - 2:00 PM",
    "description": "Spring Fling with Tiny Tails Petting Zoo, bounce house, carnival games, and Easter Egg Hunts. Age ranges for egg hunts: 3 and under, 4-7 years old, 8-12 years old. Easter Bunny available for photo ops.",
    "additional_details": "Artisan's Market from 10 AM to 2 PM. Event held in the Front Meadow at Rockbridge Church.",
    "source_file": "7221fbbf04560902163647547a7be386.JPG"
  },
  {
    "activity_name": "Bunny Hop Bash",
    "location": "Chick-fil-A Great Oaks, 113 Deer Ridge Dr, Round Rock, TX",
    "date": "2025-04-20",
    "time": "3:00 PM - 5:00 PM",
    "description": "Easter celebration featuring the Easter Bunny, face painting, cookie decorating, spring arts & crafts, Chick-fil-A cow, and music.",
    "additional_details": "Chick-fil-A Easter Basket Raffle. You will have to buy a meal per person for access to the event.",
    "source_file": "857b807248ecac5367e0c087abe7947d.JPG"
  },
  {
    "activity_name": "2025 EGGStravaganza at North Austin Y",
    "location": "North Austin YMCA, 1006 W Rundberg Ln, Austin, TX 78758-6741, United States",
    "date": "2025-04-13",
    "time": "12:00 PM - 3:00 PM",
    "description": "Free spring fun for the whole family with egg hunts, games, activities, and local community vendors. Open to all.",
    "additional_details": "Hosted by Greater Austin YMCA and North Austin YMCA. Public event. Tickets available at operations.daxko.com.",
    "source_file": "7c44df1f1d0fe54e6019cac77702ef62.JPG"
  },
  {
    "activity_name": "Spring Fling Festival 2025",
    "location": "The Mason Homestead, 1101 S Bagdad Rd, Leander, TX 78641, United States",
    "date": "2025-04-12",
    "time": "11:00 AM - 3:00 PM",
    "description": "A magical day for all ages featuring bounce houses, soft play area, photo ops with the Easter Bunny, real unicorns, crafts, and bubbles.",
    "additional_details": "Entry is FREE. Unicorn rides and photo ops are FREE for the first hour. After 12:00 PM, unicorn rides and photo ops are $10 each.",
    "source_file": "1454a95f39dd67cf2e776b94a2664b40.JPG"
  },
  {
    "activity_name": "Community Easter Egg Hunt",
    "location": "Faith Lutheran Church, 6600 Woodrow Ave, Austin, TX, United States, 78757",
    "date": "2025-04-12",
    "time": "11:00 AM - 1:00 PM",
    "description": "Annual Community Easter egg hunt for all ages.",
    "additional_details": "Free, family-friendly event.",
    "source_file": "d9fa43ad368f0fae58e37a17995f3727.JPG"
  },
  {
    "activity_name": "Squirrel Fest 2025",
    "location": "Pease Park, 1178 Kingsbury St, Austin, TX 78703, United States",
    "date": "2025-04-12",
    "time": "4:00 PM - 8:00 PM",
    "description": "Family-friendly event with fun, food, and activities, followed by a movie on the lawn. This year's movie is The Wild Robot.",
    "additional_details": "Presented by H-E-B. Learn more at peasepark.org/squirrel-fest",
    "source_file": "b012542435841ac16741d1c37b183398.JPG"
  },
  {
    "activity_name": "Books and Bees Festival",
    "location": "4000 Galleria Pkwy, Bee Cave, TX, United States, Texas 78738",
    "date": "2025-04-12",
    "time": "1:00 PM - 4:00 PM",
    "description": "Fourth annual award-winning book and nature celebration with sixteen authors for kids, teens, and adults, nature education, crafts, and live music.",
    "additional_details": "Books available for purchase from Barnes & Noble. Free parking. Event hosted by City of Bee Cave and Bee Cave Public Library. Headline sponsor is Keystone Bank. Live music from 4-5 PM.",
    "source_file": "7d53d39d4b7b6242e833abe924b5567f.JPG"
  }
]